arfcnreference/__init__.py
arfcnreference/reference_obj.py
arfcnreference-0.1.dist-info/DESCRIPTION.rst
arfcnreference-0.1.dist-info/METADATA
arfcnreference-0.1.dist-info/RECORD
arfcnreference-0.1.dist-info/WHEEL
arfcnreference-0.1.dist-info/metadata.json
arfcnreference-0.1.dist-info/top_level.txt
