Metadata-Version: 2.0
Name: arfcnreference
Version: 0.1
Summary: A python module for referencing ARFCNs in GSM
Home-page: https://github.com/ashmastaflash/opencellid-wrapper
Author: Ash Wilson
Author-email: ash.d.wilson@gmail.com
License: Apache
Keywords: arfcn gsm reference
Platform: UNKNOWN
Classifier: Programming Language :: Python :: 2.7
